octodns_metaname/__init__.py
octodns_metaname/client.py
octodns_metaname/secrets.py
octodns_metaname/testing_resolver.py
octodns_metaname/tests/__init__.py
octodns_metaname-0.1.1.dist-info/licenses/LICENSE
octodns_metaname-0.1.1.dist-info/METADATA
octodns_metaname-0.1.1.dist-info/WHEEL
octodns_metaname-0.1.1.dist-info/entry_points.txt
octodns_metaname-0.1.1.dist-info/top_level.txt
octodns_metaname-0.1.1.dist-info/RECORD
