Metadata-Version: 2.4
Name: octodns-metaname
Version: 0.1.1
Summary: OpsDev.nz OctoDNS provider for the Metaname DNS API
Author-email: "OpsDev.nz Platform Engineering" <john@opsdev.nz>
Maintainer-email: "OpsDev.nz Platform Engineering" <john@opsdev.nz>
License-Expression: Apache-2.0
Project-URL: Homepage, https://github.com/startmeup-nz/octodns-metaname
Project-URL: Source, https://github.com/startmeup-nz/octodns-metaname
Project-URL: Issues, https://github.com/startmeup-nz/octodns-metaname/issues
Keywords: octodns,metaname,dns,opsdevnz
Classifier: Development Status :: 3 - Alpha
Classifier: Intended Audience :: Developers
Classifier: Programming Language :: Python
Classifier: Programming Language :: Python :: 3
Classifier: Programming Language :: Python :: 3.9
Classifier: Programming Language :: Python :: 3.10
Classifier: Programming Language :: Python :: 3.11
Classifier: Programming Language :: Python :: 3.12
Classifier: Programming Language :: Python :: 3.13
Classifier: Operating System :: OS Independent
Classifier: Topic :: Internet :: Name Service (DNS)
Requires-Python: >=3.9
License-File: LICENSE
Requires-Dist: octodns<2.0,>=1.5
Requires-Dist: requests>=2.31
Provides-Extra: dev
Requires-Dist: build>=1.2.2; extra == "dev"
Requires-Dist: mypy>=1.12.0; extra == "dev"
Requires-Dist: pytest>=8.3.0; extra == "dev"
Requires-Dist: pytest-cov>=5.0.0; extra == "dev"
Requires-Dist: ruff>=0.6.5; extra == "dev"
Requires-Dist: twine>=5.1.1; extra == "dev"
Requires-Dist: vcrpy>=6.0.1; extra == "dev"
Requires-Dist: types-requests>=2.31.0.20240218; extra == "dev"
Provides-Extra: test
Requires-Dist: pytest>=8.3.0; extra == "test"
Requires-Dist: pytest-cov>=5.0.0; extra == "test"
Provides-Extra: onepassword
Requires-Dist: op-opsdevnz>=0.1.4; extra == "onepassword"
Dynamic: license-file
